pysensorlinx/__init__.py
pysensorlinx/sensorlinx.py
pysensorlinx-0.1.8.dist-info/licenses/LICENSE
pysensorlinx-0.1.8.dist-info/METADATA
pysensorlinx-0.1.8.dist-info/WHEEL
pysensorlinx-0.1.8.dist-info/top_level.txt
pysensorlinx-0.1.8.dist-info/RECORD
