Metadata-Version: 2.4
Name: pysensorlinx
Version: 0.1.8
Summary: Python library for accessing SensorLinx Device Data
Author-email: Stefan Slivinski <sslivins@gmail.com>
License: MIT
Project-URL: Homepage, https://github.com/sslivins/pysensorlinx
Project-URL: Bug Tracker, https://github.com/sslivins/pysensorlinx/issues
Classifier: Programming Language :: Python :: 3
Classifier: License :: OSI Approved :: MIT License
Classifier: Operating System :: OS Independent
Requires-Python: >=3.7
License-File: LICENSE
Requires-Dist: aiohttp>=3.11.12
Requires-Dist: glom
Provides-Extra: tests
Requires-Dist: pytest>=8.3.4; extra == "tests"
Requires-Dist: pytest-asyncio>=0.25.3; extra == "tests"
Requires-Dist: aioresponses>=0.7.8; extra == "tests"
Requires-Dist: python-dotenv>=1.0.1; extra == "tests"
Dynamic: license-file
